.bumpversion.cfg
.coveragerc
.git_archival.txt
.gitattributes
.gitignore
.landscape.yaml
.stickler.yml
AUTHORS.md
CHANGELOG.md
LICENSE.txt
README.md
RELEASING.md
setup.cfg
setup.py
.github/ISSUE_TEMPLATE.md
.github/PULL_REQUEST_TEMPLATE.md
.github/workflows/ci.yaml
.github/workflows/deploy-sdist.yaml
bin/avhrr2pps.py
bin/eumgacfdr2pps.py
bin/gac2pps.py
bin/mersi22pps.py
bin/mersi2pps.py
bin/metimage2pps.py
bin/modis2pps.py
bin/seviri2pps.py
bin/slstr2pps.py
bin/vgac2pps.py
bin/viirs2pps.py
continuous_integration/environment.yaml
level1c4pps/__init__.py
level1c4pps/avhrr2pps_lib.py
level1c4pps/calibration_coefs.py
level1c4pps/eumgacfdr2pps_lib.py
level1c4pps/gac2pps_lib.py
level1c4pps/mersi2pps_lib.py
level1c4pps/metimage2pps_lib.py
level1c4pps/modis2pps_lib.py
level1c4pps/seviri2pps_lib.py
level1c4pps/slstr2pps_lib.py
level1c4pps/vgac2pps_lib.py
level1c4pps/viirs2pps_lib.py
level1c4pps.egg-info/PKG-INFO
level1c4pps.egg-info/SOURCES.txt
level1c4pps.egg-info/dependency_links.txt
level1c4pps.egg-info/not-zip-safe
level1c4pps.egg-info/requires.txt
level1c4pps.egg-info/top_level.txt
level1c4pps/tests/AVHRR-GAC_FDR_1C_N06_19810330T042358Z_19810330T060903Z_R_O_20200101T000000Z_0100.nc
level1c4pps/tests/NSS.GHRR.TN.D80003.S1147.E1332.B0630506.GC
level1c4pps/tests/TIR_calib_MSG2_IR_039.json
level1c4pps/tests/TIR_calib_MSG2_IR_087.json
level1c4pps/tests/TIR_calib_MSG2_IR_097.json
level1c4pps/tests/TIR_calib_MSG2_IR_108.json
level1c4pps/tests/TIR_calib_MSG2_IR_120.json
level1c4pps/tests/TIR_calib_MSG2_IR_134.json
level1c4pps/tests/TIR_calib_MSG2_WV_062.json
level1c4pps/tests/TIR_calib_MSG2_WV_073.json
level1c4pps/tests/TLE_tirosn.txt
level1c4pps/tests/VGAC_VJ102MOD_A2018305_1042_n004946_K005.nc
level1c4pps/tests/VGAC_VNPP02MOD_A2012365_2304_n06095_K005.nc
level1c4pps/tests/__init__.py
level1c4pps/tests/test_angles.py
level1c4pps/tests/test_avhrr2pps.py
level1c4pps/tests/test_eumgacfdr2pps.py
level1c4pps/tests/test_gac2pps.py
level1c4pps/tests/test_init.py
level1c4pps/tests/test_mersi2pps.py
level1c4pps/tests/test_modis2pps.py
level1c4pps/tests/test_seviri2pps.py
level1c4pps/tests/test_slstr2pps.py
level1c4pps/tests/test_vgac2pps.py
level1c4pps/tests/test_viirs2pps.py