Metadata-Version: 2.1
Name: level1c4pps
Version: 0.2.37
Summary: Tools to convert various satellite level-1 data formats to NWCSAF/PPS level-1c format
Home-page: https://github.com/foua-pps/level1c4pps
Author: NWCSAF PPS Team et al.
Author-email: 6160529+ninahakansson@users.noreply.github.com
Classifier: Development Status :: 3 - Alpha
Classifier: Intended Audience :: Science/Research
Classifier: License :: OSI Approved :: GNU General Public License v3 or later (GPLv3+)
Classifier: Operating System :: OS Independent
Classifier: Programming Language :: Python
Classifier: Topic :: Scientific/Engineering
Requires-Python: >=3.7
Provides-Extra: gaclac
Provides-Extra: seviri
License-File: LICENSE.txt
License-File: AUTHORS.md
